{
  "db_name": "PostgreSQL",
  "query": "\n  SELECT start_time, end_time\n    FROM streams\n   WHERE channel_id = $1\n     AND start_time > $2\n     AND end_time IS NOT NULL\nORDER BY start_time DESC\n        ",
  "describe": {
    "columns": [
      {
        "ordinal": 0,
        "name": "start_time",
        "type_info": "Timestamptz"
      },
      {
        "ordinal": 1,
        "name": "end_time",
        "type_info": "Timestamptz"
      }
    ],
    "parameters": {
      "Left": [
        "Int4",
        "Timestamptz"
      ]
    },
    "nullable": [
      true,
      true
    ]
  },
  "hash": "75f85975d553f8bc7f252c63313ff4ac83a83e989951f50a0008a6e3f220016e"
}
